CHANGELOG
LICENSE
MANIFEST.in
README
README.md
requirements-performance.txt
requirements.txt
setup.cfg
setup.py
aiohttp_swagger/__init__.py
aiohttp_swagger/helpers/__init__.py
aiohttp_swagger/helpers/builders.py
aiohttp_swagger/helpers/decorators.py
aiohttp_swagger/swagger_ui/index.html
aiohttp_swagger/swagger_ui/o2c.html
aiohttp_swagger/swagger_ui/swagger-ui.js
aiohttp_swagger/swagger_ui/css/print.css
aiohttp_swagger/swagger_ui/css/reset.css
aiohttp_swagger/swagger_ui/css/screen.css
aiohttp_swagger/swagger_ui/css/style.css
aiohttp_swagger/swagger_ui/css/typography.css
aiohttp_swagger/swagger_ui/fonts/DroidSans-Bold.ttf
aiohttp_swagger/swagger_ui/fonts/DroidSans.ttf
aiohttp_swagger/swagger_ui/images/collapse.gif
aiohttp_swagger/swagger_ui/images/expand.gif
aiohttp_swagger/swagger_ui/images/explorer_icons.png
aiohttp_swagger/swagger_ui/images/favicon-16x16.png
aiohttp_swagger/swagger_ui/images/favicon-32x32.png
aiohttp_swagger/swagger_ui/images/favicon.ico
aiohttp_swagger/swagger_ui/images/logo_small.png
aiohttp_swagger/swagger_ui/images/pet_store_api.png
aiohttp_swagger/swagger_ui/images/throbber.gif
aiohttp_swagger/swagger_ui/images/wordnik_api.png
aiohttp_swagger/swagger_ui/lang/ca.js
aiohttp_swagger/swagger_ui/lang/en.js
aiohttp_swagger/swagger_ui/lang/es.js
aiohttp_swagger/swagger_ui/lang/fr.js
aiohttp_swagger/swagger_ui/lang/geo.js
aiohttp_swagger/swagger_ui/lang/it.js
aiohttp_swagger/swagger_ui/lang/ja.js
aiohttp_swagger/swagger_ui/lang/ko-kr.js
aiohttp_swagger/swagger_ui/lang/pl.js
aiohttp_swagger/swagger_ui/lang/pt.js
aiohttp_swagger/swagger_ui/lang/ru.js
aiohttp_swagger/swagger_ui/lang/tr.js
aiohttp_swagger/swagger_ui/lang/translator.js
aiohttp_swagger/swagger_ui/lang/zh-cn.js
aiohttp_swagger/swagger_ui/lib/backbone-min.js
aiohttp_swagger/swagger_ui/lib/es5-shim.js
aiohttp_swagger/swagger_ui/lib/handlebars-4.0.5.js
aiohttp_swagger/swagger_ui/lib/highlight.9.1.0.pack.js
aiohttp_swagger/swagger_ui/lib/highlight.9.1.0.pack_extended.js
aiohttp_swagger_fix.egg-info/PKG-INFO
aiohttp_swagger_fix.egg-info/SOURCES.txt
aiohttp_swagger_fix.egg-info/dependency_links.txt
aiohttp_swagger_fix.egg-info/requires.txt
aiohttp_swagger_fix.egg-info/top_level.txt