Metadata-Version: 2.1
Name: aiohttp-swagger-fix
Version: 1.0.16
Summary: Swagger API Documentation builder for aiohttp server
Home-page: https://github.com/daanklijn/aiohttp-swagger
Author: Daan Klijn
Author-email: daanklijn0@gmail.com
License: BSD
Platform: UNKNOWN
Classifier: Environment :: Console
Classifier: Intended Audience :: System Administrators
Classifier: Intended Audience :: Other Audience
Classifier: License :: OSI Approved :: BSD License
Classifier: Operating System :: MacOS
Classifier: Operating System :: Microsoft :: Windows
Classifier: Operating System :: POSIX
Classifier: Programming Language :: Python :: 3.5
Classifier: Programming Language :: Python :: 3.6
Classifier: Programming Language :: Python :: 3.7
Classifier: Programming Language :: Python :: 3.8
Classifier: Topic :: Security
Provides-Extra: performance
